panforge/__init__.py
panforge/report.py
panforge/primitives/base.css
panforge/primitives/cortex.png
panforge/primitives/footer.j2
panforge/primitives/header.j2
panforge/primitives/html_head.j2
panforge/primitives/icon-alert.svg
panforge/primitives/icon-cancel.svg
panforge/primitives/icon-checkmark.svg
panforge/primitives/icon-notify.svg
panforge/primitives/icon-unchecked.svg
panforge/primitives/logo.png
panforge/primitives/prisma.png
panforge/primitives/section_head.j2
panforge/primitives/stats_block.j2
panforge/primitives/strata.png
panforge/primitives/table.j2
panforge/primitives/title.j2
panforge-0.0.0.1.dist-info/LICENSE
panforge-0.0.0.1.dist-info/METADATA
panforge-0.0.0.1.dist-info/WHEEL
panforge-0.0.0.1.dist-info/top_level.txt
panforge-0.0.0.1.dist-info/RECORD
