Metadata-Version: 2.1
Name: panforge
Version: 0.0.0.1
Summary: Document generation library
Home-page: https://paloaltonetworks.com
Author: Andrew Mallory
Author-email: amallory@paloaltonetworks.com
License: UNKNOWN
Platform: UNKNOWN
Classifier: Programming Language :: Python :: 3
Classifier: License :: OSI Approved :: MIT License
Classifier: Operating System :: OS Independent
Requires-Python: >=3.6
Requires-Dist: requests
Requires-Dist: jinja2
Requires-Dist: jsonpath-rw
Requires-Dist: pyyaml
